README.md
setup.cfg
setup.py
snapcast/__init__.py
snapcast.egg-info/PKG-INFO
snapcast.egg-info/SOURCES.txt
snapcast.egg-info/dependency_links.txt
snapcast.egg-info/requires.txt
snapcast.egg-info/top_level.txt
snapcast/client/__init__.py
snapcast/client/gstreamer.py
snapcast/client/messages.py
snapcast/control/__init__.py
snapcast/control/client.py
snapcast/control/group.py
snapcast/control/protocol.py
snapcast/control/server.py
snapcast/control/stream.py