Metadata-Version: 1.1
Name: snapcast
Version: 2.3.7
Summary: Control Snapcast.
Home-page: https://github.com/happyleavesaoc/python-snapcast/
Author: happyleaves
Author-email: happyleaves.tfr@gmail.com
License: MIT
Platform: UNKNOWN
Classifier: License :: OSI Approved :: MIT License
Classifier: Operating System :: OS Independent
Classifier: Programming Language :: Python :: 3
